{
  "author": "dandev486",
  "name": "monokuro-green",
  "type": "dark",
  "colors": {
    "activityBar.activeBackground": "#9575CD88",
    "activityBar.activeBorder": "#9575CD88",
    "activityBar.activeFocusBorder": "#9575CD88",
    "activityBar.background": "#1C1C1C",
    "activityBar.border": "#9575CD88",
    "activityBar.foreground": "#9575CD",
    "activityBar.inactiveForeground": "#9575CD88",
    "activityBarBadge.background": "#9575CD",
    "activityBarBadge.foreground": "#1C1C1C",
    "badge.background": "#1C1C1C",
    "badge.foreground": "#9575CD",
    "breadcrumb.activeSelectionForeground": "#9575CD",
    "breadcrumb.background": "#1C1C1C",
    "breadcrumb.focusForeground": "#9575CD",
    "breadcrumb.foreground": "#9575CD88",
    "breadcrumbPicker.background": "#1C1C1C",
    "button.background": "#1C1C1C",
    "button.foreground": "#9575CD",
    "button.hoverBackground": "#1C1C1C88",
    "checkbox.background": "#1C1C1C",
    "checkbox.border": "#9575CD88",
    "checkbox.foreground": "#9575CD",
    "debugConsole.infoForeground": "#9575CD",
    "debugConsole.warningForeground": "#9575CD",
    "debugConsole.errorForeground": "#9575CD",
    "debugConsole.sourceForeground": "#9575CD",
    "debugConsoleInputIcon.Foreground": "#9575CD",
    "debugExceptionWidget.background": "#1C1C1C",
    "debugExceptionWidget.border": "#9575CD88",
    "debugIcon.breakpointCurrentStackframeForeground": "#9575CD",
    "debugIcon.breakpointDisabledForeground": "#9575CD33",
    "debugIcon.breakpointForeground": "#9575CD",
    "debugIcon.breakpointStackframeForeground": "#9575CD",
    "debugIcon.breakpointUnverifiedForeground": "#9575CD",
    "debugIcon.continueForeground": "#9575CD",
    "debugIcon.disconnectForeground": "#9575CD",
    "debugIcon.pauseForeground": "#9575CD",
    "debugIcon.restartForeground": "#9575CD",
    "debugIcon.startForeground": "#9575CD",
    "debugIcon.stepBackForeground": "#9575CD",
    "debugIcon.stepIntoForeground": "#9575CD",
    "debugIcon.stepOutForeground": "#9575CD",
    "debugIcon.stepOverForeground": "#9575CD",
    "debugIcon.stopForeground": "#9575CD",
    "debugTokenExpression.name": "#9575CD",
    "debugTokenExpression.value": "#9575CD88",
    "debugTokenExpression.string": "#9575CD88",
    "debugTokenExpression.boolean": "#9575CD88",
    "debugTokenExpression.number": "#9575CD88",
    "debugTokenExpression.error": "#9575CD88",
    "debugToolBar.background": "#1C1C1C",
    "debugToolBar.border": "#9575CD88",
    "descriptionForeground": "#9575CD",
    "diffEditor.border": "#9575CD88",
    "diffEditor.insertedTextBackground": "#9575CD33",
    "diffEditor.removedTextBackground": "#9575CD33",
    "dropdown.background": "#1C1C1C",
    "dropdown.border": "#9575CD88",
    "dropdown.foreground": "#9575CD",
    "dropdown.listBackground": "#1C1C1C",
    "editor.background": "#1C1C1C",
    "editor.findMatchBackground": "#9575CD88",
    "editor.findMatchBorder": "#9575CD88",
    "editor.findMatchHighlightBackground": "#1C1C1C",
    "editor.findMatchHighlightBorder": "#9575CD88",
    "editor.findRangeHighlightBackground": "#1C1C1C",
    "editor.findRangeHighlightBorder": "#9575CD88",
    "editor.focusedStackFrameHighlightBackground": "#1C1C1C",
    "editor.foldBackground": "#1C1C1C",
    "editor.foreground": "#9575CD",
    "editor.hoverHighlightBackground": "#1C1C1C",
    "editor.inactiveSelectionBackground": "#1C1C1C",
    "editor.lineHighlightBackground": "#9575CD11",
    "editor.lineHighlightBorder": "#9575CD11",
    "editor.rangeHighlightBackground": "#1C1C1C",
    "editor.rangeHighlightBorder": "#9575CD88",
    "editor.selectionBackground": "#9575CD33",
    "editor.selectionForeground": "#9575CD",
    "editor.selectionHighlightBackground": "#1C1C1C",
    "editor.selectionHighlightBorder": "#9575CD88",
    "editor.snippetFinalTabstopHighlightBackground": "#1C1C1C",
    "editor.snippetFinalTabstopHighlightBorder": "#9575CD88",
    "editor.snippetTabstopHighlightBackground": "#1C1C1C",
    "editor.snippetTabstopHighlightBorder": "#9575CD88",
    "editor.stackFrameHighlightBackground": "#1C1C1C",
    "editor.symbolHighlightBackground": "#9575CD33",
    "editor.symbolHighlightBorder": "#9575CD88",
    "editor.wordHighlightBackground": "#9575CD33",
    "editor.wordHighlightBorder": "#9575CD88",
    "editor.wordHighlightStrongBackground": "#9575CD88",
    "editor.wordHighlightStrongBorder": "#9575CD88",
    "editorBracketMatch.background": "#1C1C1C",
    "editorBracketMatch.border": "#9575CD88",
    "editorCodeLens.foreground": "#9575CD",
    "editorCursor.background": "#1C1C1C",
    "editorCursor.foreground": "#9575CD",
    "editorError.border": "#1C1C1C",
    "editorError.foreground": "#9575CD",
    "editorGroup.border": "#9575CD88",
    "editorGroup.dropBackground": "#9575CD33",
    "editorGroup.emptyBackground": "#1C1C1C",
    "editorGroup.focusedEmptyBorder": "#9575CD88",
    "editorGroupHeader.noTabsBackground": "#1C1C1C",
    "editorGroupHeader.tabsBackground": "#1C1C1C",
    "editorGroupHeader.tabsBorder": "#9575CD88",
    "editorGutter.addedBackground": "#9575CD33",
    "editorGutter.background": "#1C1C1C",
    "editorGutter.commentRangeForeground": "#9575CD33",
    "editorGutter.deletedBackground": "#9575CD33",
    "editorGutter.modifiedBackground": "#9575CD33",
    "editorHint.border": "#9575CD88",
    "editorHint.foreground": "#9575CD",
    "editorHoverWidget.background": "#1C1C1C",
    "editorHoverWidget.border": "#9575CD88",
    "editorHoverWidget.foreground": "#9575CD",
    "editorHoverWidget.statusBarBackground": "#9575CD33",
    "editorIndentGuide.activeBackground": "#9575CD33",
    "editorIndentGuide.background": "#9575CD11",
    "editorInfo.border": "#1C1C1C",
    "editorInfo.foreground": "#9575CD33",
    "editorLightBulb.foreground": "#9575CD88",
    "editorLightBulbAutoFix.foreground": "#9575CD88",
    "editorLineNumber.activeForeground": "#9575CD",
    "editorLineNumber.foreground": "#9575CD33",
    "editorLink.activeForeground": "#9575CD",
    "editorMarkerNavigation.background": "#9575CD33",
    "editorMarkerNavigationError.background": "#9575CD33",
    "editorMarkerNavigationInfo.background": "#9575CD33",
    "editorMarkerNavigationWarning.background": "#9575CD33",
    "editorOverviewRuler.addedForeground": "#9575CD33",
    "editorOverviewRuler.border": "#9575CD88",
    "editorOverviewRuler.bracketMatchForeground": "#9575CD33",
    "editorOverviewRuler.commonContentForeground": "#9575CD33",
    "editorOverviewRuler.currentContentForeground": "#9575CD33",
    "editorOverviewRuler.deletedForeground": "#9575CD33",
    "editorOverviewRuler.errorForeground": "#9575CD88",
    "editorOverviewRuler.findMatchForeground": "#9575CD33",
    "editorOverviewRuler.incomingContentForeground": "#9575CD33",
    "editorOverviewRuler.infoForeground": "#9575CD33",
    "editorOverviewRuler.modifiedForeground": "#9575CD33",
    "editorOverviewRuler.rangeHighlightForeground": "#9575CD33",
    "editorOverviewRuler.selectionHighlightForeground": "#9575CD33",
    "editorOverviewRuler.warningForeground": "#9575CD33",
    "editorOverviewRuler.wordHighlightForeground": "#9575CD33",
    "editorOverviewRuler.wordHighlightStrongForeground": "#9575CD33",
    "editorPane.background": "#9575CD33",
    "editorRuler.foreground": "#9575CD",
    "editorSuggestWidget.background": "#1C1C1C",
    "editorSuggestWidget.border": "#9575CD88",
    "editorSuggestWidget.foreground": "#9575CD",
    "editorSuggestWidget.highlightForeground": "#9575CD",
    "editorSuggestWidget.selectedBackground": "#9575CD88",
    "editorUnnecessaryCode.border": "#9575CD88",
    "editorUnnecessaryCode.opacity": "#9575CD33",
    "editorWarning.border": "#1C1C1C",
    "editorWarning.foreground": "#9575CD33",
    "editorWhitespace.foreground": "#9575CD33",
    "editorWidget.background": "#1C1C1C",
    "editorWidget.border": "#9575CD88",
    "editorWidget.foreground": "#9575CD",
    "editorWidget.resizeBorder": "#9575CD88",
    "errorForeground": "#9575CD",
    "extensionBadge.remoteBackground": "#1C1C1C",
    "extensionBadge.remoteForeground": "#9575CD",
    "extensionButton.prominentBackground": "#1C1C1C",
    "extensionButton.prominentForeground": "#9575CD",
    "extensionButton.prominentHoverBackground": "#1C1C1C",
    "focusBorder": "#9575CD88",
    "foreground": "#9575CD",
    "gitDecoration.addedResourceForeground": "#9575CD",
    "gitDecoration.conflictingResourceForeground": "#9575CD",
    "gitDecoration.deletedResourceForeground": "#9575CD",
    "gitDecoration.ignoredResourceForeground": "#9575CD88",
    "gitDecoration.modifiedResourceForeground": "#9575CD",
    "gitDecoration.submoduleResourceForeground": "#9575CD",
    "gitDecoration.untrackedResourceForeground": "#9575CD",
    "icon.foreground": "#9575CD",
    "imagePreview.border": "#9575CD88",
    "input.background": "#1C1C1C",
    "input.border": "#9575CD88",
    "input.foreground": "#9575CD",
    "input.placeholderForeground": "#9575CD88",
    "inputOption.activeBackground": "#9575CD33",
    "inputOption.activeBorder": "#9575CD88",
    "inputValidation.errorBackground": "#1C1C1C",
    "inputValidation.errorBorder": "#9575CD88",
    "inputValidation.errorForeground": "#9575CD",
    "inputValidation.infoBackground": "#1C1C1C",
    "inputValidation.infoBorder": "#9575CD88",
    "inputValidation.infoForeground": "#9575CD",
    "inputValidation.warningBackground": "#1C1C1C",
    "inputValidation.warningBorder": "#9575CD33",
    "inputValidation.warningForeground": "#9575CD",
    "list.activeSelectionBackground": "#9575CD",
    "list.activeSelectionForeground": "#1C1C1C",
    "list.dropBackground": "#9575CD33",
    "list.errorForeground": "#9575CD",
    "list.filterMatchBackground": "#1C1C1C",
    "list.filterMatchBorder": "#9575CD88",
    "list.focusBackground": "#9575CD88",
    "list.focusForeground": "#9575CD",
    "list.highlightForeground": "#9575CD",
    "list.hoverBackground": "#9575CD88",
    "list.hoverForeground": "#9575CD",
    "list.inactiveFocusBackground": "#9575CD33",
    "list.inactiveSelectionBackground": "#9575CD33",
    "list.inactiveSelectionForeground": "#9575CD",
    "list.invalidItemForeground": "#9575CD",
    "list.warningForeground": "#9575CD",
    "listFilterWidget.background": "#1C1C1C",
    "listFilterWidget.noMatchesOutline": "#9575CD88",
    "listFilterWidget.outline": "#9575CD",
    "menu.background": "#1C1C1C",
    "menu.border": "#9575CD88",
    "menu.foreground": "#9575CD",
    "menu.selectionBackground": "#9575CD88",
    "menu.selectionBorder": "#9575CD88",
    "menu.selectionForeground": "#1C1C1C",
    "menu.separatorBackground": "#9575CD88",
    "menubar.selectionBackground": "#9575CD33",
    "menubar.selectionBorder": "#9575CD88",
    "menubar.selectionForeground": "#9575CD",
    "merge.border": "#9575CD88",
    "merge.commonContentBackground": "#1C1C1C",
    "merge.commonHeaderBackground": "#1C1C1C",
    "merge.currentContentBackground": "#1C1C1C",
    "merge.currentHeaderBackground": "#1C1C1C",
    "merge.incomingContentBackground": "#1C1C1C",
    "merge.incomingHeaderBackground": "#1C1C1C",
    "minimap.errorHighlight": "#9575CD",
    "minimap.findMatchHighlight": "#9575CD33",
    "minimap.selectionHighlight": "#9575CD33",
    "minimap.warningHighlight": "#9575CD88",
    "minimapGutter.addedBackground": "#47802b",
    "minimapGutter.deletedBackground": "#ff0000",
    "minimapGutter.modifiedBackground": "#045658",
    "notificationCenter.border": "#9575CD88",
    "notificationCenterHeader.background": "#1C1C1C",
    "notificationCenterHeader.foreground": "#9575CD",
    "notificationLink.foreground": "#9575CD",
    "notificationToast.border": "#9575CD88",
    "notifications.background": "#1C1C1C",
    "notifications.border": "#9575CD88",
    "notifications.foreground": "#9575CD",
    "notificationsErrorIcon.foreground": "#9575CD",
    "notificationsInfoIcon.foreground": "#9575CD",
    "notificationsWarningIcon.foreground": "#9575CD",
    "panel.background": "#1C1C1C",
    "panel.border": "#9575CD88",
    "panelInput.border": "#9575CD88",
    "panelTitle.activeBorder": "#9575CD88",
    "panelTitle.activeForeground": "#9575CD",
    "panelTitle.inactiveForeground": "#9575CD88",
    "peekView.border": "#9575CD88",
    "peekViewEditor.background": "#1C1C1C",
    "peekViewEditor.matchHighlightBackground": "#1C1C1C",
    "peekViewEditor.matchHighlightBorder": "#9575CD88",
    "peekViewEditorGutter.background": "#1C1C1C",
    "peekViewResult.background": "#1C1C1C",
    "peekViewResult.fileForeground": "#9575CD",
    "peekViewResult.lineForeground": "#9575CD",
    "peekViewResult.matchHighlightBackground": "#1C1C1C",
    "peekViewResult.selectionBackground": "#1C1C1C",
    "peekViewResult.selectionForeground": "#9575CD",
    "peekViewTitle.background": "#1C1C1C",
    "peekViewTitleDescription.foreground": "#9575CD",
    "peekViewTitleLabel.foreground": "#9575CD",
    "pickerGroup.border": "#9575CD88",
    "pickerGroup.foreground": "#9575CD",
    "problemsErrorIcon.foreground": "#9575CD",
    "problemsInfoIcon.foreground": "#9575CD33",
    "problemsWarningIcon.foreground": "#9575CD33",
    "progressBar.background": "#9575CD88",
    "quickInput.background": "#1C1C1C",
    "quickInput.foreground": "#9575CD",
    "scrollbar.shadow": "#9575CD33",
    "scrollbarSlider.activeBackground": "#9575CD33",
    "scrollbarSlider.background": "#9575CD33",
    "scrollbarSlider.hoverBackground": "#9575CD33",
    "searchEditor.findMatchBackground": "#1C1C1C",
    "searchEditor.findMatchBorder": "#9575CD88",
    "searchEditor.textInputBorder": "#9575CD88",
    "selection.background": "#9575CD88",
    "settings.checkboxBackground": "#1C1C1C",
    "settings.checkboxBorder": "#9575CD88",
    "settings.checkboxForeground": "#9575CD",
    "settings.dropdownBackground": "#1C1C1C",
    "settings.dropdownBorder": "#9575CD88",
    "settings.dropdownForeground": "#9575CD",
    "settings.dropdownListBorder": "#9575CD88",
    "settings.headerForeground": "#9575CD",
    "settings.modifiedItemIndicator": "#9575CD88",
    "settings.numberInputBackground": "#1C1C1C",
    "settings.numberInputBorder": "#9575CD88",
    "settings.numberInputForeground": "#9575CD",
    "settings.textInputBackground": "#1C1C1C",
    "settings.textInputBorder": "#9575CD88",
    "settings.textInputForeground": "#9575CD",
    "sideBar.background": "#1C1C1C",
    "sideBar.border": "#9575CD88",
    "sideBar.dropBackground": "#9575CD33",
    "sideBar.foreground": "#9575CD",
    "sideBarSectionHeader.background": "#9575CD33",
    "sideBarSectionHeader.border": "#9575CD88",
    "sideBarSectionHeader.foreground": "#9575CD",
    "sideBarTitle.foreground": "#9575CD",
    "statusBar.background": "#9575CD33",
    "statusBar.border": "#9575CD88",
    "statusBar.debuggingBackground": "#9575CD",
    "statusBar.debuggingBorder": "#9575CD88",
    "statusBar.debuggingForeground": "#1C1C1C",
    "statusBar.foreground": "#9575CD",
    "statusBar.noFolderBackground": "#1C1C1C",
    "statusBar.noFolderBorder": "#9575CD88",
    "statusBar.noFolderForeground": "#9575CD",
    "statusBarItem.activeBackground": "#1C1C1C",
    "statusBarItem.hoverBackground": "#1C1C1C",
    "statusBarItem.prominentBackground": "#1C1C1C",
    "statusBarItem.prominentForeground": "#9575CD",
    "statusBarItem.prominentHoverBackground": "#1C1C1C",
    "statusBarItem.remoteBackground": "#1C1C1C",
    "statusBarItem.remoteForeground": "#9575CD",
    "symbolIcon.arrayForeground": "#9575CD",
    "symbolIcon.booleanForeground": "#9575CD",
    "symbolIcon.classForeground": "#9575CD",
    "symbolIcon.colorForeground": "#9575CD",
    "symbolIcon.constantForeground": "#9575CD",
    "symbolIcon.constructorForeground": "#9575CD",
    "symbolIcon.enumeratorForeground": "#9575CD",
    "symbolIcon.enumeratorMemberForeground": "#9575CD",
    "symbolIcon.eventForeground": "#9575CD",
    "symbolIcon.fieldForeground": "#9575CD",
    "symbolIcon.fileForeground": "#9575CD",
    "symbolIcon.folderForeground": "#9575CD",
    "symbolIcon.functionForeground": "#9575CD",
    "symbolIcon.interfaceForeground": "#9575CD",
    "symbolIcon.keyForeground": "#9575CD",
    "symbolIcon.keywordForeground": "#9575CD",
    "symbolIcon.methodForeground": "#9575CD",
    "symbolIcon.moduleForeground": "#9575CD",
    "symbolIcon.namespaceForeground": "#9575CD",
    "symbolIcon.nullForeground": "#9575CD",
    "symbolIcon.numberForeground": "#9575CD",
    "symbolIcon.objectForeground": "#9575CD",
    "symbolIcon.operatorForeground": "#9575CD",
    "symbolIcon.packageForeground": "#9575CD",
    "symbolIcon.propertyForeground": "#9575CD",
    "symbolIcon.referenceForeground": "#9575CD",
    "symbolIcon.snippetForeground": "#9575CD",
    "symbolIcon.stringForeground": "#9575CD",
    "symbolIcon.structForeground": "#9575CD",
    "symbolIcon.textForeground": "#9575CD",
    "symbolIcon.typeParameterForeground": "#9575CD",
    "symbolIcon.unitForeground": "#9575CD",
    "symbolIcon.variableForeground": "#9575CD",
    "tab.activeBackground": "#9575CD33",
    "tab.activeBorder": "#1C1C1C",
    "tab.activeBorderTop": "#1C1C1C",
    "tab.activeForeground": "#9575CD",
    "tab.activeModifiedBorder": "#9575CD88",
    "tab.border": "#1C1C1C",
    "tab.hoverBackground": "#9575CD33",
    "tab.hoverBorder": "#1C1C1C",
    "tab.inactiveBackground": "#1C1C1C",
    "tab.inactiveForeground": "#9575CD88",
    "tab.inactiveModifiedBorder": "#1C1C1C",
    "tab.unfocusedActiveBackground": "#9575CD33",
    "tab.unfocusedActiveBorder": "#1C1C1C",
    "tab.unfocusedActiveBorderTop": "#1C1C1C",
    "tab.unfocusedActiveForeground": "#9575CD",
    "tab.unfocusedActiveModifiedBorder": "#1C1C1C",
    "tab.unfocusedHoverBackground": "#9575CD33",
    "tab.unfocusedHoverBorder": "#1C1C1C",
    "tab.unfocusedInactiveForeground": "#9575CD88",
    "tab.unfocusedInactiveModifiedBorder": "#1C1C1C",
    "terminal.ansiBlack": "#9575CD88",
    "terminal.ansiBlue": "#9575CD88",
    "terminal.ansiBrightBlack": "#9575CD",
    "terminal.ansiBrightBlue": "#9575CD",
    "terminal.ansiBrightCyan": "#9575CD",
    "terminal.ansiBrightGreen": "#9575CD",
    "terminal.ansiBrightMagenta": "#9575CD",
    "terminal.ansiBrightRed": "#9575CD",
    "terminal.ansiBrightWhite": "#9575CD",
    "terminal.ansiBrightYellow": "#9575CD",
    "terminal.ansiCyan": "#9575CD88",
    "terminal.ansiGreen": "#9575CD88",
    "terminal.ansiMagenta": "#9575CD88",
    "terminal.ansiRed": "#9575CD88",
    "terminal.ansiWhite": "#9575CD88",
    "terminal.ansiYellow": "#9575CD88",
    "terminal.background": "#1C1C1C",
    "terminal.border": "#9575CD88",
    "terminal.foreground": "#9575CD",
    "terminal.selectionBackground": "#9575CD33",
    "terminalCursor.background": "#1C1C1C",
    "terminalCursor.foreground": "#9575CD",
    "textBlockQuote.background": "#1C1C1C",
    "textBlockQuote.border": "#9575CD88",
    "textCodeBlock.background": "#1C1C1C",
    "textLink.activeForeground": "#9575CD",
    "textLink.foreground": "#9575CD88",
    "textPreformat.foreground": "#9575CD",
    "textSeparator.foreground": "#9575CD",
    "titleBar.activeBackground": "#1C1C1C",
    "titleBar.activeForeground": "#9575CD",
    "titleBar.border": "#9575CD88",
    "titleBar.inactiveBackground": "#1C1C1C",
    "titleBar.inactiveForeground": "#9575CD",
    "tree.indentGuidesStroke": "#9575CD",
    "walkThrough.embeddedEditorBackground": "#1C1C1C",
    "welcomePage.background": "#1C1C1C",
    "welcomePage.buttonBackground": "#1C1C1C",
    "welcomePage.buttonHoverBackground": "#1C1C1C",
    "widget.shadow": "#9575CD33",
    "window.activeBorder": "#9575CD88",
    "window.inactiveBorder": "#9575CD33"
  },
  "tokenColors": [
    {
      "scope": ["comment"],
      "settings": {
        "foreground": "#9575CD33"
      }
    },
    {
      "scope": ["keyword", "storage"],
      "settings": {
        "foreground": "#9575CD88"
      }
    },
    {
      "scope": ["entity", "strong"],
      "settings": {
        "fontStyle": "bold"
      }
    },
    {
      "scope": ["invalid"],
      "settings": {
        "foreground": "#9575CD88",
        "fontStyle": "italic underline"
      }
    },
    {
      "scope": "token.info-token",
      "settings": {
        "foreground": "#316BCD"
      }
    },
    {
      "scope": "token.warn-token",
      "settings": {
        "foreground": "#CD9731"
      }
    },
    {
      "scope": "token.error-token",
      "settings": {
        "foreground": "#CD3131"
      }
    },
    {
      "scope": "token.debug-token",
      "settings": {
        "foreground": "#800080"
      }
    }
  ]
}
